zhulong2/__init__.py
zhulong2/anhui/__init__.py
zhulong2/anhui/anqing.py
zhulong2/anhui/huainan.py
zhulong2/anhui/luan.py
zhulong2/anhui/shenghui.py
zhulong2/anhui/task.py
zhulong2/anhui/wuhu.py
zhulong2/beijing/__init__.py
zhulong2/beijing/beijing.py
zhulong2/beijing/task.py
zhulong2/chongqing/__init__.py
zhulong2/chongqing/chongqing.py
zhulong2/chongqing/task.py
zhulong2/fujian/__init__.py
zhulong2/fujian/fuzhou.py
zhulong2/fujian/longyan.py
zhulong2/fujian/nanping.py
zhulong2/fujian/nanping1.py
zhulong2/fujian/ningde.py
zhulong2/fujian/putian.py
zhulong2/fujian/quanzhou.py
zhulong2/fujian/sanming.py
zhulong2/fujian/sanming1.py
zhulong2/fujian/task.py
zhulong2/fujian/xiamen.py
zhulong2/fujian/zhangzhou.py
zhulong2/gansu/__init__.py
zhulong2/gansu/jinchang.py
zhulong2/gansu/shenghui.py
zhulong2/gansu/task.py
zhulong2/guangdong/__init__.py
zhulong2/guangdong/chaozhou.py
zhulong2/guangdong/dongguan.py
zhulong2/guangdong/dongguan1.py
zhulong2/guangdong/foshan.py
zhulong2/guangdong/guangzhou.py
zhulong2/guangdong/guangzhou1.py
zhulong2/guangdong/heyuan.py
zhulong2/guangdong/huizhou.py
zhulong2/guangdong/jiangmen.py
zhulong2/guangdong/jieyang.py
zhulong2/guangdong/maoming.py
zhulong2/guangdong/meizhou.py
zhulong2/guangdong/qingyuan.py
zhulong2/guangdong/shantou.py
zhulong2/guangdong/shantou1.py
zhulong2/guangdong/shanwei.py
zhulong2/guangdong/shaoguan.py
zhulong2/guangdong/shenghui.py
zhulong2/guangdong/shenghui1.py
zhulong2/guangdong/shenzhen.py
zhulong2/guangdong/shenzhen1.py
zhulong2/guangdong/task.py
zhulong2/guangdong/yangjiang.py
zhulong2/guangdong/yunfu.py
zhulong2/guangdong/yzm_model.m
zhulong2/guangdong/zhanjiang.py
zhulong2/guangdong/zhaoqing.py
zhulong2/guangdong/zhongshan.py
zhulong2/guangdong/zhongshan1.py
zhulong2/guangdong/zhuhai.py
zhulong2/guangxi/__init__.py
zhulong2/guangxi/baise.py
zhulong2/guangxi/fangchenggang.py
zhulong2/guangxi/guigang.py
zhulong2/guangxi/guilin.py
zhulong2/guangxi/liuzhou.py
zhulong2/guangxi/nanning.py
zhulong2-5.2.61.dist-info/METADATA
zhulong2-5.2.61.dist-info/WHEEL
zhulong2-5.2.61.dist-info/top_level.txt
zhulong2-5.2.61.dist-info/RECORD
